aws_org_tree/__init__.py
aws_org_tree/__main__.py
aws_org_tree/aws_org_tree.py
aws_org_tree-0.5.1.dist-info/METADATA
aws_org_tree-0.5.1.dist-info/WHEEL
aws_org_tree-0.5.1.dist-info/entry_points.txt
aws_org_tree-0.5.1.dist-info/RECORD
