Metadata-Version: 2.1
Name: aws-org-tree
Version: 0.5.1
Summary: 
Home-page: https://github.com/iainelder/aws-org-tree
Author: Iain Samuel McLean Elder
Author-email: iain@isme.es
Requires-Python: >=3.12,<4.0
Classifier: Programming Language :: Python :: 3
Requires-Dist: anytree (>=2.12.0,<3.0.0)
Requires-Dist: boto3 (>=1.18.50,<2.0.0)
Requires-Dist: boto3-stubs[organizations] (>=1.21.42,<2.0.0)
Requires-Dist: logdecorator (>=2.2,<3.0)
Requires-Dist: mypy-boto3-organizations (>=1.26.83,<2.0.0)
Requires-Dist: orgtreepubsub (>=0.1.0,<0.2.0)
Requires-Dist: urllib3 (<2)
Project-URL: Repository, https://github.com/iainelder/aws-org-tree
